dsniff-0.1.5.dist-info/licenses/LICENSE
dsniff_py/__init__.py
dsniff_py/cli.py
dsniff_py/dsniff.magic
dsniff_py/dsniff.services
dsniff_py/menu.py
dsniff_py/bin/arpspoof
dsniff_py/bin/dnsspoof
dsniff_py/bin/dsniff
dsniff_py/bin/filesnarf
dsniff_py/bin/macof
dsniff_py/bin/mailsnarf
dsniff_py/bin/msgsnarf
dsniff_py/bin/sshow
dsniff_py/bin/tcpkill
dsniff_py/bin/tcpnice
dsniff_py/bin/urlsnarf
dsniff_py/bin/webmitm
dsniff-0.1.5.dist-info/METADATA
dsniff-0.1.5.dist-info/WHEEL
dsniff-0.1.5.dist-info/entry_points.txt
dsniff-0.1.5.dist-info/top_level.txt
dsniff-0.1.5.dist-info/RECORD
