Metadata-Version: 2.4
Name: dsniff
Version: 0.1.5
Summary: This package provides a new Python wrapper for the dsniff network sniffer suite (originally by Dug Song).
Author: Modified Dug Song dsniff by Josh James
Author-email: Josh James <josh@rocketnow.com>
License-Expression: BSD-Source-Code
Keywords: networking,security,packet-sniffer,dsniff
Requires-Python: >=3.6
License-File: LICENSE
Dynamic: author
Dynamic: license-file
Dynamic: requires-python
